probe_basic/__init__.py
probe_basic/_version.py
probe_basic/about.ui
probe_basic/menubar.yml
probe_basic/probe_basic.py
probe_basic/probe_basic.qrc
probe_basic/probe_basic.qss
probe_basic/probe_basic.ui
probe_basic/probe_basic.yml
probe_basic/probe_basic_vertical.ui
probe_basic/fonts/BebasKai.ttf
probe_basic/images/a_minus_jog_button.png
probe_basic/images/a_plus_jog_button.png
probe_basic/images/atc_spindle_tool.png
probe_basic/images/atc_spindle_tool_dimensioned.png
probe_basic/images/b_minus_jog_button.png
probe_basic/images/b_plus_jog_button.png
probe_basic/images/back_left_outside_corner.png
probe_basic/images/back_middle_outside_edge.png
probe_basic/images/back_right_outside_corner.png
probe_basic/images/boss_pocket_3d_image.png
probe_basic/images/boss_round.png
probe_basic/images/ccw_arrow.png
probe_basic/images/clearance.png
probe_basic/images/cw_arrow.png
probe_basic/images/delete.png
probe_basic/images/down_arrow.png
probe_basic/images/drill_dim.png
probe_basic/images/drill_dims_white.png
probe_basic/images/extra_probe_depth.png
probe_basic/images/folder_up.png
probe_basic/images/front_left_outside_corner.png
probe_basic/images/front_middle_edge.png
probe_basic/images/front_right_outside_corner.png
probe_basic/images/inside_back_left_corner.png
probe_basic/images/inside_back_right_corner.png
probe_basic/images/inside_corners_3d_image.png
probe_basic/images/inside_front_left_corner.png
probe_basic/images/inside_front_right_corner.png
probe_basic/images/left_arrow.png
probe_basic/images/left_side_edge.png
probe_basic/images/max_distance.png
probe_basic/images/max_xy_distance.png
probe_basic/images/max_z_distance.png
probe_basic/images/new_file.png
probe_basic/images/new_folder.png
probe_basic/images/permissions.png
probe_basic/images/probe_basic_icon.png
probe_basic/images/probe_cal_id_ring.png
probe_basic/images/probe_cal_round_boss.png
probe_basic/images/probe_cal_round_pocket.png
probe_basic/images/probe_cal_square_boss.png
probe_basic-0.3.3.dist-info/LICENSE.md
probe_basic-0.3.3.dist-info/METADATA
probe_basic-0.3.3.dist-info/WHEEL
probe_basic-0.3.3.dist-info/entry_points.txt
probe_basic-0.3.3.dist-info/top_level.txt
probe_basic-0.3.3.dist-info/RECORD
