Metadata-Version: 2.1
Name: probe-basic
Version: 0.3.3
Summary: Probe Basic - A QtPyVCP based Virtual Control Panel for LinuxCNC
Home-page: https://github.com/kcjengr/probe_basic
Author: Chris Polanski
Author-email: 
License: UNKNOWN
Download-URL: https://github.com/kcjengr/probe_basic/tarball/master
Platform: UNKNOWN
Requires-Dist: qtpyvcp (>=0.3.9)
